README.md
raven-bash
setup.py
logger/__init__.py
logger/raven_logger.py
raven_bash.egg-info/PKG-INFO
raven_bash.egg-info/SOURCES.txt
raven_bash.egg-info/dependency_links.txt
raven_bash.egg-info/entry_points.txt
raven_bash.egg-info/not-zip-safe
raven_bash.egg-info/requires.txt
raven_bash.egg-info/top_level.txt