Metadata-Version: 1.1
Name: raven-bash
Version: 1.0
Summary: Raven Sentry client for Bash.
Home-page: https://github.com/hareevs/raven-bash
Author: Viktor Stiskala
Author-email: viktor@stiskala.cz
License: Apache License 2.0
Keywords: raven sentry bash
Platform: UNKNOWN
Classifier: Development Status :: 4 - Beta
Classifier: Intended Audience :: Developers
Classifier: License :: OSI Approved :: Apache Software License
Classifier: Programming Language :: Python :: 3 :: Only
Classifier: Programming Language :: Python :: 3.4
